setup.py
artichoke/__init__.py
artichoke/application.py
artichoke/authenticator.py
artichoke/controller.py
artichoke/forms.py
artichoke/mail_traceback.py
artichoke/server.py
artichoke/template.py
artichoke/thread_locals.py
artichoke.egg-info/PKG-INFO
artichoke.egg-info/SOURCES.txt
artichoke.egg-info/dependency_links.txt
artichoke.egg-info/entry_points.txt
artichoke.egg-info/not-zip-safe
artichoke.egg-info/requires.txt
artichoke.egg-info/top_level.txt