Metadata-Version: 1.1
Name: artichoke
Version: 0.4
Summary: Simple and Lightweight WSGI Web Framework
Home-page: http://www.axantlabs.com/artichoke
Author: AXANT
Author-email: tech@axant.it
License: GPL
Keywords: wsgi web simple light
Platform: UNKNOWN
Classifier: Development Status :: 5 - Production/Stable
Classifier: License :: OSI Approved :: GNU General Public License (GPL)
Classifier: Topic :: Internet :: WWW/HTTP :: WSGI :: Middleware
Classifier: Programming Language :: Python
Classifier: Topic :: Internet :: WWW/HTTP :: WSGI
Classifier: Topic :: Internet :: WWW/HTTP :: WSGI :: Application
Classifier: Topic :: Software Development :: Libraries :: Application Frameworks
Classifier: Environment :: Web Environment
